SimpleMachines
