Metadata-Version: 1.0
Name: SimpleMachines
Version: 1.2
Summary: THis package help people who work with basic calculations of simple machines
Home-page: UNKNOWN
Author: Taha Huzeyfe Aktas
Author-email: taha.huzeyfe@gmail.com
License: UNKNOWN
Platform: UNKNOWN
